b2brilliant_sdk/__init__.py
b2brilliant_sdk/agent.py
b2brilliant_sdk/api_client.py
b2brilliant_sdk/business.py
b2brilliant_sdk/campaigns.py
b2brilliant_sdk/endpoints.py
b2brilliant_sdk/exceptions.py
b2brilliant_sdk/user.py
b2brilliant_sdk-0.1.2.dist-info/METADATA
b2brilliant_sdk-0.1.2.dist-info/WHEEL
b2brilliant_sdk-0.1.2.dist-info/RECORD
