Metadata-Version: 2.4
Name: b2brilliant_sdk
Version: 0.1.2
Summary: The Official Python SDK for the B2Brilliant Campaign Agent API
Project-URL: Homepage, https://b2brilliant.app
Project-URL: Bug Tracker, https://github.com/h8ngryDev4Hire/b2brilliant-sdk/issues
Author: B2Brilliant
Classifier: License :: Other/Proprietary License
Classifier: Operating System :: OS Independent
Classifier: Programming Language :: Python :: 3
Requires-Python: >=3.8
Requires-Dist: requests>=2.25.0
